[
    {
        "text": "Main Navigation",
        "heading": "true",
        "translate": "sidebar.heading.HEADER"
    },
    {
        "text": "Dashboard",
        "sref": "app.dashboard",
        "icon": "icon-speedometer",
        "label": "label label-info"
    },

    {
        "text": "Groups",
        "sref": "app.groups",
        "icon": "icon-people",
        "translate": "sidebar.nav.GROUPS"
    },
    {
        "text": "Sites",
        "sref": "app.sites",
        "icon": "icon-doc",
        "translate": "sidebar.nav.SITES"
    },
    {
        "text": "Devices",
        "sref": "app.devices",
        "icon": "icon-docs",
        "translate": "sidebar.nav.DEVICES"
    },
    {
        "text": "Users",
        "sref": "app.users",
        "icon": "icon-user",
        "translate": "sidebar.nav.USERS"
    }
]